{
  "id": "geografia",
  "name": "Geografia",
  "questions": [
    "q-000003",
    "q-000006",
    "q-000008",
    "q-000010"
  ],
  "subcategories": [
    {
      "id": "capitales",
      "name": "Capitales",
      "questions": [
        "q-000003",
        "q-000006",
        "q-000008"
      ]
    },
    {
      "id": "oceanos",
      "name": "Oceanos",
      "questions": [
        "q-000010"
      ]
    }
  ],
  "stats": {
    "total": 4,
    "easy": 4,
    "medium": 0,
    "hard": 0
  },
  "updated_at": "2026-06-24"
}
