{
  "id": "q-000497",
  "status": "published",
  "language": "es",
  "category": "ciencia",
  "subcategories": [
    "quimica"
  ],
  "difficulty": "easy",
  "question": "Elige la respuesta correcta para esta pista de ciencia: “Qué elemento químico tiene el símbolo Md”?",
  "answers": [
    {
      "text": "californio",
      "correct": false
    },
    {
      "text": "mendelevio",
      "correct": true
    },
    {
      "text": "seaborgio",
      "correct": false
    },
    {
      "text": "lawrencio",
      "correct": false
    }
  ],
  "explanation": "El símbolo Md corresponde al mendelevio.",
  "sources": [
    {
      "title": "IUPAC Periodic Table of the Elements",
      "url": "https://iupac.org/what-we-do/periodic-table-of-elements/"
    }
  ],
  "tags": [
    "quimica",
    "tabla-periodica",
    "mendelevio",
    "repaso"
  ],
  "created_at": "2026-06-24",
  "updated_at": "2026-06-24"
}
