{
  "id": "q-003708",
  "status": "published",
  "language": "es",
  "category": "cine-tv",
  "subcategories": [
    "lenguaje-cinematografico"
  ],
  "difficulty": "hard",
  "question": "En lenguaje audiovisual, ¿qué término se define como “efecto de cambio de focal combinado con movimiento de cámara”?",
  "answers": [
    {
      "text": "travelling",
      "correct": false
    },
    {
      "text": "blooper",
      "correct": false
    },
    {
      "text": "neorrealismo italiano",
      "correct": false
    },
    {
      "text": "dolly zoom",
      "correct": true
    }
  ],
  "explanation": "El término audiovisual definido es dolly zoom.",
  "sources": [
    {
      "title": "Wikipedia - dolly zoom",
      "url": "https://es.wikipedia.org/wiki/dolly_zoom"
    }
  ],
  "tags": [
    "cine",
    "lenguaje-audiovisual",
    "dolly-zoom"
  ],
  "created_at": "2026-06-24",
  "updated_at": "2026-06-24"
}
