{
  "id": "q-007820",
  "status": "published",
  "language": "es",
  "category": "geografia",
  "subcategories": [
    "capitales",
    "latitud"
  ],
  "difficulty": "hard",
  "question": "¿Qué capital está más al norte: São Tomé, Tripoli, Saipan o Yaren?",
  "answers": [
    {
      "text": "Saipan",
      "correct": false
    },
    {
      "text": "Tripoli",
      "correct": true
    },
    {
      "text": "Yaren",
      "correct": false
    },
    {
      "text": "São Tomé",
      "correct": false
    }
  ],
  "explanation": "Entre las opciones, Tripoli es la capital situada a mayor latitud norte.",
  "sources": [
    {
      "title": "CIA World Factbook",
      "url": "https://www.cia.gov/the-world-factbook/"
    }
  ],
  "tags": [
    "geografia",
    "capitales",
    "latitud"
  ],
  "created_at": "2026-06-24",
  "updated_at": "2026-06-24"
}
