{
  "id": "q-007975",
  "status": "published",
  "language": "es",
  "category": "geografia",
  "subcategories": [
    "idiomas"
  ],
  "difficulty": "medium",
  "question": "¿Qué idioma aparece como oficial o principal en Nicaragua?",
  "answers": [
    {
      "text": "ay",
      "correct": false
    },
    {
      "text": "amárico",
      "correct": false
    },
    {
      "text": "xhosa",
      "correct": false
    },
    {
      "text": "español",
      "correct": true
    }
  ],
  "explanation": "Entre los idiomas registrados para Nicaragua figura el español.",
  "sources": [
    {
      "title": "CIA World Factbook",
      "url": "https://www.cia.gov/the-world-factbook/"
    }
  ],
  "tags": [
    "geografia",
    "idiomas",
    "nicaragua"
  ],
  "created_at": "2026-06-24",
  "updated_at": "2026-06-24"
}
