{
  "id": "q-004744",
  "status": "published",
  "language": "es",
  "category": "matematicas",
  "subcategories": [
    "porcentajes"
  ],
  "difficulty": "medium",
  "question": "¿Cuál es el 25% de 380?",
  "answers": [
    {
      "text": "95",
      "correct": true
    },
    {
      "text": "90",
      "correct": false
    },
    {
      "text": "105",
      "correct": false
    },
    {
      "text": "100",
      "correct": false
    }
  ],
  "explanation": "El 25% de 380 es 380 × 25/100 = 95.",
  "sources": [
    {
      "title": "OpenStax - Algebra and Trigonometry 2e",
      "url": "https://openstax.org/details/books/algebra-and-trigonometry-2e"
    }
  ],
  "tags": [
    "porcentajes",
    "aritmetica"
  ],
  "created_at": "2026-06-24",
  "updated_at": "2026-06-24"
}
