{
  "id": "q-008796",
  "status": "published",
  "language": "es",
  "category": "lengua",
  "subcategories": [
    "verbos"
  ],
  "difficulty": "hard",
  "question": "¿Entre yo hube cantado, yo cantaré, yo cantaba y yo canto, qué forma verbal corresponde a pretérito anterior?",
  "answers": [
    {
      "text": "yo canto",
      "correct": false
    },
    {
      "text": "yo hube cantado",
      "correct": true
    },
    {
      "text": "yo cantaba",
      "correct": false
    },
    {
      "text": "yo cantaré",
      "correct": false
    }
  ],
  "explanation": "La forma “yo hube cantado” corresponde a pretérito anterior.",
  "sources": [
    {
      "title": "Real Academia Española",
      "url": "https://www.rae.es/"
    }
  ],
  "tags": [
    "verbos",
    "preterito-anterior"
  ],
  "created_at": "2026-06-24",
  "updated_at": "2026-06-24"
}
