{
  "id": "q-000558",
  "status": "published",
  "language": "es",
  "category": "geografia",
  "subcategories": [
    "codigos-iso"
  ],
  "difficulty": "hard",
  "question": "¿Cuál es el código ISO 3166-1 alfa-2 de Burkina Faso?",
  "answers": [
    {
      "text": "CG",
      "correct": false
    },
    {
      "text": "BF",
      "correct": true
    },
    {
      "text": "SM",
      "correct": false
    },
    {
      "text": "EH",
      "correct": false
    }
  ],
  "explanation": "El código ISO 3166-1 alfa-2 de Burkina Faso es BF.",
  "sources": [
    {
      "title": "ISO - ISO 3166 Country Codes",
      "url": "https://www.iso.org/iso-3166-country-codes.html"
    }
  ],
  "tags": [
    "iso-3166",
    "codigos-de-pais",
    "burkina-faso"
  ],
  "created_at": "2026-06-24",
  "updated_at": "2026-06-24"
}
