{
  "id": "q-002936",
  "status": "published",
  "language": "es",
  "category": "literatura",
  "subcategories": [
    "obras-y-autores-avanzado"
  ],
  "difficulty": "hard",
  "question": "¿Quién es el autor de Grandes esperanzas?",
  "answers": [
    {
      "text": "Charles Dickens",
      "correct": true
    },
    {
      "text": "William Faulkner",
      "correct": false
    },
    {
      "text": "Miguel de Unamuno",
      "correct": false
    },
    {
      "text": "Rómulo Gallegos",
      "correct": false
    }
  ],
  "explanation": "Grandes esperanzas fue escrito por Charles Dickens.",
  "sources": [
    {
      "title": "Wikipedia - Grandes esperanzas",
      "url": "https://es.wikipedia.org/wiki/Grandes_esperanzas"
    }
  ],
  "tags": [
    "literatura",
    "autores",
    "charles-dickens"
  ],
  "created_at": "2026-06-24",
  "updated_at": "2026-06-24"
}
