{
  "id": "q-008876",
  "status": "published",
  "language": "es",
  "category": "lengua",
  "subcategories": [
    "lexico"
  ],
  "difficulty": "medium",
  "question": "¿Entre fuerte, subir, permitir y preguntar, qué palabra tiene significado opuesto a “responder”?",
  "answers": [
    {
      "text": "permitir",
      "correct": false
    },
    {
      "text": "subir",
      "correct": false
    },
    {
      "text": "preguntar",
      "correct": true
    },
    {
      "text": "fuerte",
      "correct": false
    }
  ],
  "explanation": "“preguntar” y “responder” tienen significados opuestos.",
  "sources": [
    {
      "title": "Real Academia Española",
      "url": "https://www.rae.es/"
    }
  ],
  "tags": [
    "antonimos",
    "preguntar",
    "responder"
  ],
  "created_at": "2026-06-24",
  "updated_at": "2026-06-24"
}
