{
  "id": "q-006985",
  "status": "published",
  "language": "es",
  "category": "entretenimiento",
  "subcategories": [
    "videojuegos"
  ],
  "difficulty": "medium",
  "question": "¿Qué compañía o estudio se asocia con “Tomb Raider”?",
  "answers": [
    {
      "text": "Santa Monica Studio",
      "correct": false
    },
    {
      "text": "Core Design",
      "correct": true
    },
    {
      "text": "CD Projekt Red",
      "correct": false
    },
    {
      "text": "Valve",
      "correct": false
    }
  ],
  "explanation": "“Tomb Raider” se asocia con Core Design.",
  "sources": [
    {
      "title": "The Strong National Museum of Play",
      "url": "https://www.museumofplay.org/"
    }
  ],
  "tags": [
    "videojuegos",
    "tomb-raider",
    "core-design"
  ],
  "created_at": "2026-06-24",
  "updated_at": "2026-06-24"
}
