{
  "id": "q-009478",
  "status": "published",
  "language": "es",
  "category": "matematicas",
  "subcategories": [
    "porcentajes"
  ],
  "difficulty": "medium",
  "question": "¿Qué resultado da calcular el 65% de 400?",
  "answers": [
    {
      "text": "260",
      "correct": true
    },
    {
      "text": "270",
      "correct": false
    },
    {
      "text": "265",
      "correct": false
    },
    {
      "text": "255",
      "correct": false
    }
  ],
  "explanation": "El 65% de 400 se calcula como 400 × 65/100 = 260.",
  "sources": [
    {
      "title": "OpenStax Algebra and Trigonometry 2e",
      "url": "https://openstax.org/details/books/algebra-and-trigonometry-2e"
    }
  ],
  "tags": [
    "porcentajes",
    "aritmetica"
  ],
  "created_at": "2026-06-24",
  "updated_at": "2026-06-24"
}
