{
  "id": "q-003357",
  "status": "published",
  "language": "es",
  "category": "gastronomia",
  "subcategories": [
    "cereales-y-masas"
  ],
  "difficulty": "hard",
  "question": "¿Qué base farinácea o cereal se asocia de forma característica con gnocchi tradicionales?",
  "answers": [
    {
      "text": "hojas rellenas de arroz o carne",
      "correct": false
    },
    {
      "text": "patata y harina",
      "correct": true
    },
    {
      "text": "mijo perlado",
      "correct": false
    },
    {
      "text": "harina y huevo",
      "correct": false
    }
  ],
  "explanation": "Gnocchi tradicionales se asocia característicamente con patata y harina.",
  "sources": [
    {
      "title": "Wikipedia - gnocchi tradicionales",
      "url": "https://es.wikipedia.org/wiki/gnocchi_tradicionales"
    }
  ],
  "tags": [
    "gastronomia",
    "cereales",
    "gnocchi-tradicionales"
  ],
  "created_at": "2026-06-24",
  "updated_at": "2026-06-24"
}
