{
  "id": "q-003640",
  "status": "published",
  "language": "es",
  "category": "arte",
  "subcategories": [
    "arquitectura-avanzada"
  ],
  "difficulty": "hard",
  "question": "¿Qué estilo o corriente arquitectónica se asocia con Seagram Building?",
  "answers": [
    {
      "text": "estilo internacional",
      "correct": true
    },
    {
      "text": "neoclasicismo",
      "correct": false
    },
    {
      "text": "metabolismo o arquitectura modular",
      "correct": false
    },
    {
      "text": "arquitectura islámica",
      "correct": false
    }
  ],
  "explanation": "Seagram Building se asocia con estilo internacional.",
  "sources": [
    {
      "title": "Wikipedia - Seagram Building",
      "url": "https://es.wikipedia.org/wiki/Seagram_Building"
    }
  ],
  "tags": [
    "arte",
    "arquitectura",
    "estilo-internacional"
  ],
  "created_at": "2026-06-24",
  "updated_at": "2026-06-24"
}
