{
  "id": "q-003650",
  "status": "published",
  "language": "es",
  "category": "gastronomia",
  "subcategories": [
    "ingredientes"
  ],
  "difficulty": "hard",
  "question": "Qué plato de esta lista tiene como ingrediente destacado pescado frito”?",
  "answers": [
    {
      "text": "meat pie",
      "correct": false
    },
    {
      "text": "fish and chips",
      "correct": true
    },
    {
      "text": "ceviche",
      "correct": false
    },
    {
      "text": "pretzel",
      "correct": false
    }
  ],
  "explanation": "fish and chips destaca por el uso de pescado frito.",
  "sources": [
    {
      "title": "Encyclopaedia Britannica - Food",
      "url": "https://www.britannica.com/topic/food"
    }
  ],
  "tags": [
    "ingredientes",
    "pescado-frito",
    "repaso"
  ],
  "created_at": "2026-06-24",
  "updated_at": "2026-06-24"
}