{
  "id": "q-005862",
  "status": "published",
  "language": "es",
  "category": "ciencia",
  "subcategories": [
    "nutricion"
  ],
  "difficulty": "medium",
  "question": "¿Con qué función se relaciona especialmente la vitamina E?",
  "answers": [
    {
      "text": "función tiroidea",
      "correct": false
    },
    {
      "text": "formación de ADN",
      "correct": false
    },
    {
      "text": "protección antioxidante",
      "correct": true
    },
    {
      "text": "coagulación sanguínea",
      "correct": false
    }
  ],
  "explanation": "La vitamina E se relaciona con protección antioxidante.",
  "sources": [
    {
      "title": "MedlinePlus",
      "url": "https://medlineplus.gov/"
    }
  ],
  "tags": [
    "nutricion",
    "vitamina-e"
  ],
  "created_at": "2026-06-24",
  "updated_at": "2026-06-24"
}
