{
  "id": "q-008894",
  "status": "published",
  "language": "es",
  "category": "lengua",
  "subcategories": [
    "gramatica"
  ],
  "difficulty": "medium",
  "question": "¿Entre masculino o ambiguo, femenino, femenino con artículo el por a tónica y masculino, qué género gramatical corresponde a “la sal”?",
  "answers": [
    {
      "text": "femenino con artículo el por a tónica",
      "correct": false
    },
    {
      "text": "masculino o ambiguo",
      "correct": false
    },
    {
      "text": "masculino",
      "correct": false
    },
    {
      "text": "femenino",
      "correct": true
    }
  ],
  "explanation": "La forma “la sal” corresponde a femenino.",
  "sources": [
    {
      "title": "Real Academia Española",
      "url": "https://www.rae.es/"
    }
  ],
  "tags": [
    "genero-gramatical",
    "la-sal"
  ],
  "created_at": "2026-06-24",
  "updated_at": "2026-06-24"
}
