{
  "id": "q-005232",
  "status": "published",
  "language": "es",
  "category": "arte-y-literatura",
  "subcategories": [
    "artistas"
  ],
  "difficulty": "hard",
  "question": "¿Entre Miguel Ángel, Henri Matisse, Gustav Klimt y Pablo Picasso, qué artista se vincula con Modernismo y Austria?",
  "answers": [
    {
      "text": "Miguel Ángel",
      "correct": false
    },
    {
      "text": "Pablo Picasso",
      "correct": false
    },
    {
      "text": "Gustav Klimt",
      "correct": true
    },
    {
      "text": "Henri Matisse",
      "correct": false
    }
  ],
  "explanation": "Gustav Klimt se vincula con Modernismo y Austria.",
  "sources": [
    {
      "title": "Encyclopaedia Britannica",
      "url": "https://www.britannica.com/"
    }
  ],
  "tags": [
    "arte",
    "modernismo",
    "austria"
  ],
  "created_at": "2026-06-24",
  "updated_at": "2026-06-24"
}
