{
  "id": "q-000532",
  "status": "published",
  "language": "es",
  "category": "ciencia",
  "subcategories": [
    "quimica",
    "tabla-periodica"
  ],
  "difficulty": "medium",
  "question": "¿Cuál es el símbolo químico del elemento Germanio?",
  "answers": [
    {
      "text": "Ge",
      "correct": true
    },
    {
      "text": "Cd",
      "correct": false
    },
    {
      "text": "Cm",
      "correct": false
    },
    {
      "text": "Rg",
      "correct": false
    }
  ],
  "explanation": "El símbolo del elemento Germanio es Ge.",
  "sources": [
    {
      "title": "IUPAC - Periodic Table of Elements",
      "url": "https://iupac.org/what-we-do/periodic-table-of-elements/"
    }
  ],
  "tags": [
    "quimica",
    "tabla-periodica",
    "germanio"
  ],
  "created_at": "2026-06-24",
  "updated_at": "2026-06-24"
}
