{
  "id": "q-007487",
  "status": "published",
  "language": "es",
  "category": "gastronomia",
  "subcategories": [
    "tecnicas"
  ],
  "difficulty": "medium",
  "question": "¿Qué técnica culinaria consiste en cocinar lentamente con algo de líquido?",
  "answers": [
    {
      "text": "freír",
      "correct": false
    },
    {
      "text": "tostar",
      "correct": false
    },
    {
      "text": "amasar",
      "correct": false
    },
    {
      "text": "brasear",
      "correct": true
    }
  ],
  "explanation": "brasear consiste en cocinar lentamente con algo de líquido.",
  "sources": [
    {
      "title": "Encyclopaedia Britannica - Food",
      "url": "https://www.britannica.com/topic/food"
    }
  ],
  "tags": [
    "gastronomia",
    "tecnicas",
    "brasear"
  ],
  "created_at": "2026-06-24",
  "updated_at": "2026-06-24"
}
