{
  "id": "q-011544",
  "status": "published",
  "language": "es",
  "category": "entretenimiento",
  "subcategories": [
    "videojuegos"
  ],
  "difficulty": "easy",
  "question": "¿Qué personaje se asocia con “Minecraft”?",
  "answers": [
    {
      "text": "Scorpion",
      "correct": false
    },
    {
      "text": "Ryu",
      "correct": false
    },
    {
      "text": "Steve",
      "correct": true
    },
    {
      "text": "Lara Croft",
      "correct": false
    }
  ],
  "explanation": "Steve es un personaje asociado con “Minecraft”.",
  "sources": [
    {
      "title": "The Strong National Museum of Play",
      "url": "https://www.museumofplay.org/"
    }
  ],
  "tags": [
    "videojuegos",
    "minecraft",
    "steve"
  ],
  "created_at": "2026-06-24",
  "updated_at": "2026-06-24"
}
