{
  "id": "q-019184",
  "status": "published",
  "language": "es",
  "category": "matematicas",
  "subcategories": [
    "algebra"
  ],
  "difficulty": "medium",
  "question": "¿Cuáles son las raíces de la ecuación x² +2x -3 = 0?",
  "answers": [
    {
      "text": "3 y -1",
      "correct": false
    },
    {
      "text": "-3 y 1",
      "correct": true
    },
    {
      "text": "-3 y -1",
      "correct": false
    },
    {
      "text": "-2 y 0",
      "correct": false
    }
  ],
  "explanation": "La ecuación se factoriza como (x - -3)(x - 1) = 0, por lo que las raíces son -3 y 1.",
  "sources": [
    {
      "title": "OpenStax - Algebra and Trigonometry",
      "url": "https://openstax.org/details/books/algebra-and-trigonometry-2e"
    }
  ],
  "tags": [
    "ecuaciones",
    "algebra"
  ],
  "created_at": "2026-06-25",
  "updated_at": "2026-06-25"
}
