{
  "id": "q-014943",
  "status": "published",
  "language": "es",
  "category": "tecnologia",
  "subcategories": [
    "numeracion-binaria"
  ],
  "difficulty": "medium",
  "question": "¿Cómo se escribe 488 en sistema binario?",
  "answers": [
    {
      "text": "111101010",
      "correct": false
    },
    {
      "text": "111101001",
      "correct": false
    },
    {
      "text": "111100111",
      "correct": false
    },
    {
      "text": "111101000",
      "correct": true
    }
  ],
  "explanation": "La representación binaria de 488 es 111101000.",
  "sources": [
    {
      "title": "MDN Web Docs",
      "url": "https://developer.mozilla.org/"
    }
  ],
  "tags": [
    "binario"
  ],
  "created_at": "2026-06-24",
  "updated_at": "2026-06-24"
}
