{
  "id": "q-019963",
  "status": "published",
  "language": "es",
  "category": "tecnologia",
  "subcategories": [
    "programacion"
  ],
  "difficulty": "hard",
  "question": "¿Cuál es el resultado decimal de aplicar AND bit a bit entre 125 y 213?",
  "answers": [
    {
      "text": "82",
      "correct": false
    },
    {
      "text": "253",
      "correct": false
    },
    {
      "text": "85",
      "correct": true
    },
    {
      "text": "168",
      "correct": false
    }
  ],
  "explanation": "El operador AND bit a bit conserva solo los bits que están activos en ambos números; 125 AND 213 = 85.",
  "sources": [
    {
      "title": "MDN Web Docs",
      "url": "https://developer.mozilla.org/"
    }
  ],
  "tags": [
    "bits",
    "operadores"
  ],
  "created_at": "2026-06-25",
  "updated_at": "2026-06-25"
}
