{
  "id": "q-024569",
  "status": "published",
  "language": "es",
  "category": "tecnologia",
  "subcategories": [
    "sistemas-numericos"
  ],
  "difficulty": "medium",
  "question": "¿Cuál es la notación hexadecimal del número decimal 81?",
  "answers": [
    {
      "text": "0x50",
      "correct": false
    },
    {
      "text": "0xA2",
      "correct": false
    },
    {
      "text": "0x52",
      "correct": false
    },
    {
      "text": "0x51",
      "correct": true
    }
  ],
  "explanation": "Al convertir 81 a base 16 se obtiene 0x51.",
  "sources": [
    {
      "title": "MDN Web Docs",
      "url": "https://developer.mozilla.org/"
    }
  ],
  "tags": [
    "hexadecimal",
    "conversion"
  ],
  "created_at": "2026-06-25",
  "updated_at": "2026-06-25"
}
