{
  "id": "q-023905",
  "status": "published",
  "language": "es",
  "category": "lengua",
  "subcategories": [
    "retorica"
  ],
  "difficulty": "hard",
  "question": "¿Qué fenómeno retórico se muestra en “Hay un palacio y un río y un lago y un puente viejo”?",
  "answers": [
    {
      "text": "elipsis",
      "correct": false
    },
    {
      "text": "símil",
      "correct": false
    },
    {
      "text": "polisíndeton",
      "correct": true
    },
    {
      "text": "ironía",
      "correct": false
    }
  ],
  "explanation": "“Hay un palacio y un río y un lago y un puente viejo” se clasifica como polisíndeton.",
  "sources": [
    {
      "title": "Real Academia Española",
      "url": "https://www.rae.es/"
    }
  ],
  "tags": [
    "retorica",
    "figuras-literarias"
  ],
  "created_at": "2026-06-25",
  "updated_at": "2026-06-25"
}
