{
  "id": "q-021395",
  "status": "published",
  "language": "es",
  "category": "deporte",
  "subcategories": [
    "mundiales"
  ],
  "difficulty": "hard",
  "question": "¿Cuál de estos elementos ocurrió antes: Chile 1962, Argentina 1978, Estados Unidos 1994 o Sudáfrica 2010?",
  "answers": [
    {
      "text": "Estados Unidos 1994",
      "correct": false
    },
    {
      "text": "Argentina 1978",
      "correct": false
    },
    {
      "text": "Chile 1962",
      "correct": true
    },
    {
      "text": "Sudáfrica 2010",
      "correct": false
    }
  ],
  "explanation": "Chile 1962 es la opción correcta porque su fecha asociada es 1962.",
  "sources": [
    {
      "title": "FIFA",
      "url": "https://www.fifa.com/"
    }
  ],
  "tags": [
    "mundial",
    "futbol"
  ],
  "created_at": "2026-06-25",
  "updated_at": "2026-06-25"
}
