{
  "id": "q-022430",
  "status": "published",
  "language": "es",
  "category": "gastronomia",
  "subcategories": [
    "platos-avanzados"
  ],
  "difficulty": "hard",
  "question": "¿Qué opción relaciona bien risotto con su origen y base?",
  "answers": [
    {
      "text": "risotto — Italia — arroz arborio",
      "correct": true
    },
    {
      "text": "risotto — Levante mediterráneo — garbanzo",
      "correct": false
    },
    {
      "text": "risotto — Vietnam — pan",
      "correct": false
    },
    {
      "text": "risotto — Japón — rebozado ligero",
      "correct": false
    }
  ],
  "explanation": "La asociación correcta para risotto es Italia y arroz arborio.",
  "sources": [
    {
      "title": "Larousse Gastronomique",
      "url": "https://www.larousse.fr/encyclopedie/gastronomie"
    }
  ],
  "tags": [
    "platos",
    "origen",
    "ingredientes"
  ],
  "created_at": "2026-06-25",
  "updated_at": "2026-06-25"
}
